README.rst
setup.cfg
setup.py
acme/__init__.py
acme/dchat.py
acme.dchat.egg-info/PKG-INFO
acme.dchat.egg-info/SOURCES.txt
acme.dchat.egg-info/dependency_links.txt
acme.dchat.egg-info/namespace_packages.txt
acme.dchat.egg-info/top_level.txt