Metadata-Version: 1.1
Name: acme.dchat
Version: 0.1
Summary: This software aim to provide a chatting tool with the NTT docomo API
Home-page: https://github.com/jptomo/acme.dchat
Author: Tomohiro NAKAMURA
Author-email: quickness.net@gmail.com
License: Apache Software License
Keywords: chat
Platform: UNKNOWN
Classifier: Development Status :: 4 - Beta
Classifier: License :: OSI Approved :: Apache Software License
Classifier: Programming Language :: Python :: 3.4
